icsystemutils/__init__.py
icsystemutils/main_cli.py
icsystemutils/py.typed
icsystemutils/cpu/__init__.py
icsystemutils/cpu/cpu_info.py
icsystemutils/cpu/proc_info.py
icsystemutils/cpu/process.py
icsystemutils/cpu/sys_ctl.py
icsystemutils/gpu/__init__.py
icsystemutils/gpu/gpu_info.py
icsystemutils/gpu/nvidia_smi.py
icsystemutils/monitor/__init__.py
icsystemutils/monitor/handler.py
icsystemutils/monitor/monitor.py
icsystemutils/monitor/profiler.py
icsystemutils/monitor/resource_monitor.py
icsystemutils/monitor/sample.py
icsystemutils/monitor/sampler.py
icsystemutils/monitor/tracing.py
icsystemutils/network/__init__.py
icsystemutils/network/info.py
icsystemutils/network/remote.py
icsystemutils-0.2.5.dist-info/licenses/LICENSE
icsystemutils-0.2.5.dist-info/METADATA
icsystemutils-0.2.5.dist-info/WHEEL
icsystemutils-0.2.5.dist-info/entry_points.txt
icsystemutils-0.2.5.dist-info/top_level.txt
icsystemutils-0.2.5.dist-info/RECORD
