Metadata-Version: 2.4
Name: icsystemutils
Version: 0.2.5
Summary: Utilities for interacting with system resources, e.g. cpu, network etc.
Author-email: Irish Centre for High End Computing <james.grogan@ichec.ie>
Project-URL: Repository, https://git.ichec.ie/performance/toolshed/icsystemutils
Project-URL: Homepage, https://git.ichec.ie/performance/toolshed/icsystemutils
Keywords: System Utilities,HPC
Classifier: Development Status :: 3 - Alpha
Classifier: Programming Language :: Python :: 3
Classifier: License :: OSI Approved :: GNU General Public License v3 or later (GPLv3+)
Classifier: Operating System :: OS Independent
Classifier: Topic :: System :: Distributed Computing
Requires-Python: >=3.10
License-File: LICENSE
Requires-Dist: iccore==0.2.3
Requires-Dist: psutil
Requires-Dist: fabric>=3.2.2
Provides-Extra: test
Requires-Dist: pytest; extra == "test"
Requires-Dist: pytest-cov; extra == "test"
Requires-Dist: pytest-sugar; extra == "test"
Requires-Dist: black; extra == "test"
Requires-Dist: mypy; extra == "test"
Requires-Dist: flake8; extra == "test"
Requires-Dist: pylint; extra == "test"
Dynamic: license-file
